README.md
setup.py
socketio_middleware_jwt/__init__.py
socketio_middleware_jwt.egg-info/PKG-INFO
socketio_middleware_jwt.egg-info/SOURCES.txt
socketio_middleware_jwt.egg-info/dependency_links.txt
socketio_middleware_jwt.egg-info/requires.txt
socketio_middleware_jwt.egg-info/top_level.txt