Metadata-Version: 1.0
Name: socketio-middleware-jwt
Version: 1.0
Summary: This is a middleware for jwt
Home-page: https://github.com/keyloguer/socketio_middleware_jwt
Author: Daniel Pereira Zitei, Carla de Almeida Madureira
Author-email: daniel.zitei@gmail.com, carla.almadureira@gmail.com
License: Apache License, Version 2.0
Platform: UNKNOWN
